README.txt
setup.cfg
setup.py
osc4py3/__init__.py
osc4py3/as__common.py
osc4py3/as_allthreads.py
osc4py3/as_comthreads.py
osc4py3/as_eventloop.py
osc4py3/oscbuildparse.py
osc4py3/oscchannel.py
osc4py3/oscdispatching.py
osc4py3/oscdistributing.py
osc4py3/oscmethod.py
osc4py3/oscnettools.py
osc4py3/oscpacketoptions.py
osc4py3/oscpeeradapt.py
osc4py3/oscscheduling.py
osc4py3/osctcp.py
osc4py3/osctoolspools.py
osc4py3/oscudpmc.py
osc4py3.egg-info/PKG-INFO
osc4py3.egg-info/SOURCES.txt
osc4py3.egg-info/dependency_links.txt
osc4py3.egg-info/top_level.txt
osc4py3/demos/__init__.py
osc4py3/demos/demoslogger.py
osc4py3/demos/rundemo.py
osc4py3/demos/speedudpcli.py
osc4py3/demos/speedudpcommon.py
osc4py3/demos/speedudpsrv.py
osc4py3/tests/__init__.py
osc4py3/tests/buildparse.py
osc4py3/tests/channel.py
osc4py3/tests/comthreads.py
osc4py3/tests/dispatching.py
osc4py3/tests/method.py
osc4py3/tests/nettools.py
osc4py3/tests/testslogger.py
osc4py3/tests/toolspools.py
osc4py3/tests/udp.py
osc4py3/tests/udpbc.py
osc4py3/tests/udpmc.py