Metadata-Version: 1.1
Name: osc4py3
Version: 1.0.7
Summary: Python3 package for Open Sound Control (OSC) communications.
Home-page: http://perso.limsi.fr/pointal/dev:osc4py3
Author: Laurent Pointal
Author-email: laurent.pointal@limsi.fr
License: CEA CNRS Inria Logiciel Libre License, version 2.1 (CeCILL-2.1)
Download-URL: https://sourcesup.renater.fr/projects/osc4py3/
Keywords: communication,sound,network,open sound control,osc
Platform: UNKNOWN
Classifier: Development Status :: 5 - Production/Stable
Classifier: Intended Audience :: Science/Research
Classifier: Natural Language :: English
Classifier: Operating System :: OS Independent
Classifier: Programming Language :: Python :: 3
Classifier: License :: OSI Approved :: CEA CNRS Inria Logiciel Libre License, version 2.1 (CeCILL-2.1)
Classifier: Topic :: Scientific/Engineering
Classifier: Topic :: Software Development :: Libraries :: Python Modules
Classifier: Topic :: Multimedia :: Sound/Audio
